pyLinG3D/__init__.py
pyLinG3D/linG3DAliveAll.py
pyLinG3D/linG3DAliveAll_old.py
pyLinG3D/linG3DAliveClone.py
pyLinG3D/linG3DAliveClone_old.py
pyLinG3D/linG3DAll.py
pyLinG3D/linG3DAll_old.py
pyLinG3D/linG3DClone.py
pyLinG3D/linG3DClone_old.py
pyLinG3D/utils/__init__.py
pyLinG3D/utils/base.py
pyLinG3D-0.6.dist-info/METADATA
pyLinG3D-0.6.dist-info/WHEEL
pyLinG3D-0.6.dist-info/top_level.txt
pyLinG3D-0.6.dist-info/RECORD
