Metadata-Version: 2.1
Name: pyLinG3D
Version: 0.6
Summary: Visualizing the Spatio-Temporal Dynamics of Clonal Evolution
Author: A. Hu, A.M.E. Ojwang, K.D. Olumoyin, and K.A. Rejniak
Author-email: kasia.rejniak@moffitt.org, kayode.olumoyin@moffitt.org
License: MIT
Classifier: Development Status :: 3 - Alpha
Classifier: Intended Audience :: Science/Research
Classifier: License :: OSI Approved :: MIT License
Classifier: Programming Language :: Python :: 3
Classifier: Programming Language :: Python :: 3.8
Classifier: Programming Language :: Python :: 3.9
Requires-Python: >=3.8
Requires-Dist: matplotlib (==3.5.1)
Requires-Dist: numpy (==1.21.6)
Requires-Dist: scipy (==1.7.3)
